waybacktweets/__init__.py
waybacktweets/_cli.py
waybacktweets/api/__init__.py
waybacktweets/api/export.py
waybacktweets/api/parse.py
waybacktweets/api/request.py
waybacktweets/api/visualize.py
waybacktweets/config/__init__.py
waybacktweets/config/config.py
waybacktweets/config/field_options.py
waybacktweets/exceptions/__init__.py
waybacktweets/exceptions/exceptions.py
waybacktweets/utils/__init__.py
waybacktweets/utils/utils.py
waybacktweets-1.0.dist-info/LICENSE.md
waybacktweets-1.0.dist-info/METADATA
waybacktweets-1.0.dist-info/WHEEL
waybacktweets-1.0.dist-info/entry_points.txt
waybacktweets-1.0.dist-info/RECORD
