Metadata-Version: 2.1
Name: waybacktweets
Version: 1.0
Summary: Retrieves archived tweets CDX data from the Wayback Machine, performs necessary parsing, and saves the data.
Home-page: https://github.com/claromes/waybacktweets
License: GPLv3
Keywords: Twitter,X,tweet,Internet Archive,Wayback Machine,OSINT,SOCMINT
Author: Claromes
Author-email: support@claromes.com
Requires-Python: >=3.10,<4.0
Classifier: Development Status :: 5 - Production/Stable
Classifier: Intended Audience :: Developers
Classifier: Intended Audience :: Science/Research
Classifier: License :: OSI Approved :: GNU General Public License v3 (GPLv3)
Classifier: License :: Other/Proprietary License
Classifier: Natural Language :: English
Classifier: Programming Language :: Python :: 3
Classifier: Programming Language :: Python :: 3.10
Classifier: Programming Language :: Python :: 3.11
Classifier: Programming Language :: Python :: 3.12
Classifier: Topic :: Software Development
Classifier: Topic :: Utilities
Requires-Dist: click (>=8.1.7,<9.0.0)
Requires-Dist: pandas (>=2.2.2,<3.0.0)
Requires-Dist: requests (>=2.30.0,<3.0.0)
Requires-Dist: rich (>=13.6.0,<14.0.0)
Project-URL: Documentation, https://waybacktweets.claromes.com/
Project-URL: Homepage, https://waybacktweets.claromes.com/
Project-URL: Issue Tracker, https://github.com/claromes/waybacktweets/issues
Project-URL: Repository, https://github.com/claromes/waybacktweets
